BookerAutoVideo/__init__.py
BookerAutoVideo/__main__.py
BookerAutoVideo/_autovideo.py
BookerAutoVideo/audio2txt.py
BookerAutoVideo/autovideo.py
BookerAutoVideo/autovideo_config.py
BookerAutoVideo/imgsim.py
BookerAutoVideo/keyframe.py
BookerAutoVideo/util.py
BookerAutoVideo/video2txt.py
BookerAutoVideo/asset/__init__.py
BookerAutoVideo/asset/fengmingshoushu.ttf
BookerAutoVideo/asset/jingdianyahei.ttf
BookerAutoVideo/asset/kaiti.ttf
BookerAutoVideo/asset/longyinshoushu.ttf
BookerAutoVideo/asset/shoujinti.ttf
BookerAutoVideo-2023.2.5.3.dist-info/LICENSE
BookerAutoVideo-2023.2.5.3.dist-info/METADATA
BookerAutoVideo-2023.2.5.3.dist-info/WHEEL
BookerAutoVideo-2023.2.5.3.dist-info/entry_points.txt
BookerAutoVideo-2023.2.5.3.dist-info/top_level.txt
BookerAutoVideo-2023.2.5.3.dist-info/RECORD
